charmonium/freeze/__init__.py
charmonium/freeze/config.py
charmonium/freeze/freeze_basic.py
charmonium/freeze/freeze_files.py
charmonium/freeze/freeze_function.py
charmonium/freeze/freeze_objects.py
charmonium/freeze/freeze_thirdparty.py
charmonium/freeze/freeze_type.py
charmonium/freeze/lib.py
charmonium/freeze/py.typed
charmonium/freeze/summarize_diff.py
charmonium/freeze/util.py
charmonium_freeze-0.8.5.dist-info/LICENSE
charmonium_freeze-0.8.5.dist-info/METADATA
charmonium_freeze-0.8.5.dist-info/WHEEL
charmonium_freeze-0.8.5.dist-info/RECORD
