Metadata-Version: 2.3
Name: charmonium.freeze
Version: 0.8.5
Summary: Injectively, deterministically maps arbitrary objects to hashable values
License: MIT
Keywords: freeze,hash
Author: Samuel Grayson
Author-email: sam+dev@samgrayson.me
Requires-Python: >=3.9,<4.0
Classifier: Development Status :: 4 - Beta
Classifier: Intended Audience :: Developers
Classifier: License :: OSI Approved :: MIT License
Classifier: Natural Language :: English
Classifier: Operating System :: OS Independent
Classifier: Programming Language :: Python :: 3
Classifier: Programming Language :: Python :: 3.9
Classifier: Programming Language :: Python :: 3.10
Classifier: Programming Language :: Python :: 3.11
Classifier: Programming Language :: Python :: 3.12
Classifier: Programming Language :: Python :: 3.13
Classifier: Topic :: Software Development :: Libraries :: Python Modules
Classifier: Typing :: Typed
Project-URL: Repository, https://github.com/charmoniumQ/charmonium.freeze
